setup.py
ura/__init__.py
ura/__main__.py
ura/base.py
ura/cli.py
ura/download.py
ura/globals.py
ura/init.py
ura/main.py
ura/settings.py
ura/style.py
ura/utils.py
urasunday.egg-info/PKG-INFO
urasunday.egg-info/SOURCES.txt
urasunday.egg-info/dependency_links.txt
urasunday.egg-info/entry_points.txt
urasunday.egg-info/requires.txt
urasunday.egg-info/top_level.txt