Metadata-Version: 2.1
Name: urasunday
Version: 0.0.0.0a3
Summary: A Basic Urasunday Scraper
Home-page: https://github.com/hyaku-dl/urasunday
Author: whinee
Author-email: whinyaan@pm.me
License: MIT
Project-URL: Documentation, https://ura.hyaku.download
Project-URL: Source, https://github.com/hyaku-dl/urasunday
Project-URL: Tracker, https://github.com/hyaku-dl/urasunday/issues
Keywords: python windows macos linux cli scraper downloader manga python3 urasunday
Platform: UNKNOWN
Classifier: Programming Language :: Python :: 3
Classifier: License :: OSI Approved :: MIT License
Classifier: Operating System :: OS Independent
Requires-Python: >=3.10
